cooltime/__init__.py
cooltime-1.0.3.1.dist-info/LICENSE
cooltime-1.0.3.1.dist-info/WHEEL
cooltime-1.0.3.1.dist-info/METADATA
cooltime-1.0.3.1.dist-info/RECORD
