Metadata-Version: 2.1
Name: cooltime
Version: 1.0.3.1
Summary: 全球最人性化的时间模块
Author-email: "lcctoor.com" <lcctoor@outlook.com>
Classifier: License :: OSI Approved :: Apache Software License
Requires-Dist: arts
Project-URL: HomePage, https://github.com/lcctoor/arts/tree/main/arts
